AUTHORS
LICENSE
MANIFEST.in
README.md
setup.py
better500s/__init__.py
better500s/helpers.py
better500s/middleware.py
better500s/models.py
better500s/urls.py
better500s/views.py
better500s/static/better500s/images/down-arrow.png
better500s/static/better500s/images/right-arrow.png
better500s/static/better500s/js/jquery-1.6.2.min.js
better500s/templates/better500s/500_handler.html
better500s/templates/better500s/admin_email.txt
better500s/templates/better500s/error_with_notes_email.txt
better500s/templates/better500s/feedback_saved.html
better500s/templates/better500s/traceback.html
better500s/templates/better500s/view_error.html
django_better500s.egg-info/PKG-INFO
django_better500s.egg-info/SOURCES.txt
django_better500s.egg-info/dependency_links.txt
django_better500s.egg-info/not-zip-safe
django_better500s.egg-info/top_level.txt