Metadata-Version: 1.1
Name: django-better500s
Version: 0.2
Summary: Library for Django that provides better error logging
Home-page: https://github.com/skoczen/django-better500s
Author: Steven Skoczen
Author-email: steven@agoodcloud.com
License: UNKNOWN
Platform: UNKNOWN
Classifier: Programming Language :: Python
Classifier: License :: OSI Approved :: MIT License
Classifier: Operating System :: OS Independent
Classifier: Development Status :: 4 - Beta
Classifier: Environment :: Web Environment
Classifier: Framework :: Django
Classifier: Intended Audience :: Developers
Classifier: Topic :: Internet :: WWW/HTTP
Classifier: Topic :: Software Development :: Libraries :: Python Modules
